mozlog/__init__.py
mozlog/capture.py
mozlog/commandline.py
mozlog/logtypes.py
mozlog/proxy.py
mozlog/reader.py
mozlog/stdadapter.py
mozlog/structuredlog.py
mozlog/formatters/__init__.py
mozlog/formatters/base.py
mozlog/formatters/errorsummary.py
mozlog/formatters/grouping.py
mozlog/formatters/machformatter.py
mozlog/formatters/process.py
mozlog/formatters/tbplformatter.py
mozlog/formatters/unittest.py
mozlog/formatters/xunit.py
mozlog/formatters/html/__init__.py
mozlog/formatters/html/html.py
mozlog/formatters/html/main.js
mozlog/formatters/html/style.css
mozlog/formatters/html/xmlgen.py
mozlog/handlers/__init__.py
mozlog/handlers/base.py
mozlog/handlers/bufferhandler.py
mozlog/handlers/messagehandler.py
mozlog/handlers/statushandler.py
mozlog/handlers/summaryhandler.py
mozlog/handlers/valgrindhandler.py
mozlog/pytest_mozlog/__init__.py
mozlog/pytest_mozlog/plugin.py
mozlog/scripts/__init__.py
mozlog/scripts/format.py
mozlog/scripts/logmerge.py
mozlog/scripts/unstable.py
mozlog/unstructured/__init__.py
mozlog/unstructured/logger.py
mozlog/unstructured/loggingmixin.py
mozlog/unstructured/loglistener.py
mozlog-7.1.1.dist-info/METADATA
mozlog-7.1.1.dist-info/WHEEL
mozlog-7.1.1.dist-info/entry_points.txt
mozlog-7.1.1.dist-info/top_level.txt
mozlog-7.1.1.dist-info/RECORD
