Metadata-Version: 2.1
Name: mozlog
Version: 7.1.1
Summary: Robust log handling specialized for logging in the Mozilla universe
Home-page: https://wiki.mozilla.org/Auto-tools/Projects/Mozbase
Author: Mozilla Automation and Testing Team
Author-email: tools@lists.mozilla.org
License: Mozilla Public License 2.0 (MPL 2.0)
Platform: Any
Classifier: Development Status :: 4 - Beta
Classifier: Environment :: Console
Classifier: Intended Audience :: Developers
Classifier: License :: OSI Approved :: Mozilla Public License 2.0 (MPL 2.0)
Classifier: Operating System :: OS Independent
Classifier: Programming Language :: Python :: 2.7
Classifier: Programming Language :: Python :: 3.5
Classifier: Topic :: Software Development :: Libraries :: Python Modules
Requires-Dist: blessed (>=1.19.1)
Requires-Dist: mozterm
Requires-Dist: mozfile
Requires-Dist: six (>=1.13.0)
